fauthy_sdk/client.py
fauthy_sdk/management.py
fauthy_python_sdk-0.3.0.dist-info/METADATA
fauthy_python_sdk-0.3.0.dist-info/WHEEL
fauthy_python_sdk-0.3.0.dist-info/top_level.txt
fauthy_python_sdk-0.3.0.dist-info/RECORD
