Metadata-Version: 2.4
Name: fauthy-python-sdk
Version: 0.3.0
Summary: SDK to consume Fauthy API from a FastAPI application.
Requires-Python: >=3.13
Requires-Dist: pytest>=8.4.0
Requires-Dist: requests>=2.32.3
